solicitudos/__init__.py
solicitudos-0.0.1.dist-info/licenses/LICENSE-GPLv3
solicitudos-0.0.1.dist-info/METADATA
solicitudos-0.0.1.dist-info/WHEEL
solicitudos-0.0.1.dist-info/top_level.txt
solicitudos-0.0.1.dist-info/RECORD
