Metadata-Version: 2.4
Name: solicitudos
Version: 0.0.1
Summary: A package to protect against aliased machine-translated code
Author-email: Keith Grant <kgrant@redhat.com>
License-Expression: GPL-3.0-only
Classifier: Development Status :: 1 - Planning
Classifier: Intended Audience :: Developers
Classifier: Programming Language :: Python
Classifier: Topic :: Software Development :: Libraries :: Python Modules
License-File: LICENSE-GPLv3
Dynamic: license-file
